expAscribe/__init__.py
expAscribe/draw.py
expAscribe/falsify.py
expAscribe/io_utils.py
expAscribe/itvsimu.py
expAscribe/learn.py
expAscribe/plot.py
expAscribe/quasiexp.py
expAscribe/regress.py
expAscribe/score.py
expAscribe/model/__init__.py
expAscribe/model/functional.py
expAscribe/model/voter.py
expAscribe-1.2.9.dist-info/LICENSE
expAscribe-1.2.9.dist-info/METADATA
expAscribe-1.2.9.dist-info/WHEEL
expAscribe-1.2.9.dist-info/top_level.txt
expAscribe-1.2.9.dist-info/RECORD
