Metadata-Version: 2.1
Name: expAscribe
Version: 1.2.9
Summary: ExpAscribe: a causal inference framework for quantitative experiment ascription and its derivative process. Documentation: https://seabirdshore.github.io/EAdocs/
Author: $3@6iRd5h0r3
Classifier: Programming Language :: Python :: 3
Classifier: License :: OSI Approved :: MIT License
Classifier: Operating System :: OS Independent
Requires-Python: >=3.9
License-File: LICENSE
Requires-Dist: causal-learn ==0.1.3.8
Requires-Dist: dagma ==1.1.1
Requires-Dist: dowhy ==0.11.1
Requires-Dist: networkx >=3.2.1
Requires-Dist: bayesian-optimization ==1.4.2
Requires-Dist: scikit-learn >=1.5.1
Requires-Dist: scipy >=1.11.4
Requires-Dist: statsmodels >=0.14.2
Requires-Dist: matplotlib >=3.7.0
Requires-Dist: numpy <1.26.4,>=1.23.0
Requires-Dist: pandas >=1.5.3
